{
    "city": 2,
    "initialStart": [
        11.90796,
        57.72021
    ],
    "trips": [
        {
            "summary": {
                "distance": 586.6,
                "duration": 118.8
            },
            "user": {
                "id": 1281,
                "token": "eyJhbGciOiJIUzI1NiIsInR5cCI6IkpXVCJ9.eyJpZCI6MTI4MSwicm9sZSI6InVzZXIiLCJpYXQiOjE3MDQzNjA0NDAsImV4cCI6MTczNTg5NjQ0MH0.ZzJx6-oiJF-f9bX25LeoTCIq0tt_UJjP6I5lm1i1WMM"
            },
            "coords": [
                [
                    11.90796,
                    57.72021
                ],
                [
                    11.90768,
                    57.72008
                ],
                [
                    11.90743,
                    57.71981
                ],
                [
                    11.90733,
                    57.71984
                ],
                [
                    11.90703,
                    57.72007
                ],
                [
                    11.90609,
                    57.72075
                ],
                [
                    11.9056,
                    57.72055
                ],
                [
                    11.9055,
                    57.7205
                ],
                [
                    11.90537,
                    57.72054
                ],
                [
                    11.90523,
                    57.72051
                ],
                [
                    11.90518,
                    57.72047
                ],
                [
                    11.90518,
                    57.72041
                ],
                [
                    11.90523,
                    57.72037
                ],
                [
                    11.90514,
                    57.72032
                ],
                [
                    11.9052,
                    57.72029
                ],
                [
                    11.9054,
                    57.72023
                ],
                [
                    11.90579,
                    57.72008
                ],
                [
                    11.90603,
                    57.71996
                ],
                [
                    11.90646,
                    57.71966
                ],
                [
                    11.9071,
                    57.7191
                ],
                [
                    11.9074,
                    57.7188
                ],
                [
                    11.90772,
                    57.71839
                ],
                [
                    11.90788,
                    57.71818
                ],
                [
                    11.90761,
                    57.71823
                ]
            ]
        }
    ]
}