{
    "city": 1,
    "initialStart": [
        18.04658,
        59.34059
    ],
    "trips": [
        {
            "summary": {
                "distance": 403.7,
                "duration": 89.5
            },
            "user": {
                "id": 596,
                "token": "eyJhbGciOiJIUzI1NiIsInR5cCI6IkpXVCJ9.eyJpZCI6NTk2LCJyb2xlIjoidXNlciIsImlhdCI6MTcwMjkyMTQ3NSwiZXhwIjoxNzM0NDU3NDc1fQ.1uxkDRqWymS07s-9O6wyxd7cuO8pYsQJ6nk1GcTBK8k"
            },
            "coords": [
                [
                    18.04658,
                    59.34059
                ],
                [
                    18.0466,
                    59.34057
                ],
                [
                    18.04688,
                    59.34028
                ],
                [
                    18.04699,
                    59.34031
                ],
                [
                    18.04584,
                    59.34148
                ],
                [
                    18.04575,
                    59.34155
                ],
                [
                    18.04569,
                    59.34162
                ],
                [
                    18.04562,
                    59.34169
                ],
                [
                    18.04468,
                    59.34264
                ],
                [
                    18.04458,
                    59.34275
                ],
                [
                    18.04489,
                    59.34276
                ],
                [
                    18.04488,
                    59.34285
                ],
                [
                    18.04486,
                    59.34296
                ],
                [
                    18.04512,
                    59.34297
                ]
            ]
        }
    ]
}