{
    "city": 3,
    "initialStart": [
        12.95999,
        55.59089
    ],
    "trips": [
        {
            "summary": {
                "distance": 371.3,
                "duration": 60.8
            },
            "user": {
                "id": 931,
                "token": "eyJhbGciOiJIUzI1NiIsInR5cCI6IkpXVCJ9.eyJpZCI6OTMxLCJyb2xlIjoidXNlciIsImlhdCI6MTcwNDIwOTEyNCwiZXhwIjoxNzM1NzQ1MTI0fQ.wMIiw-MKrGxXiqfQfy5yWxaPyrkhxX2BWTpGvW0wlNg"
            },
            "coords": [
                [
                    12.95999,
                    55.59089
                ],
                [
                    12.96021,
                    55.5908
                ],
                [
                    12.96097,
                    55.59049
                ],
                [
                    12.96112,
                    55.59043
                ],
                [
                    12.96124,
                    55.59037
                ],
                [
                    12.96161,
                    55.59013
                ],
                [
                    12.9617,
                    55.59007
                ],
                [
                    12.96177,
                    55.59002
                ],
                [
                    12.96201,
                    55.58987
                ],
                [
                    12.96223,
                    55.58973
                ],
                [
                    12.96232,
                    55.58967
                ],
                [
                    12.9624,
                    55.58972
                ],
                [
                    12.96248,
                    55.58976
                ],
                [
                    12.96286,
                    55.59005
                ],
                [
                    12.96287,
                    55.59006
                ],
                [
                    12.96296,
                    55.59013
                ],
                [
                    12.96317,
                    55.59029
                ],
                [
                    12.96328,
                    55.59039
                ],
                [
                    12.96338,
                    55.59035
                ],
                [
                    12.96412,
                    55.59002
                ],
                [
                    12.96417,
                    55.59
                ]
            ]
        }
    ]
}