{
    "city": 3,
    "initialStart": [
        12.9883,
        55.58852
    ],
    "trips": [
        {
            "summary": {
                "distance": 485.4,
                "duration": 107.8
            },
            "user": {
                "id": 932,
                "token": "eyJhbGciOiJIUzI1NiIsInR5cCI6IkpXVCJ9.eyJpZCI6OTMyLCJyb2xlIjoidXNlciIsImlhdCI6MTcwNDIwOTEyNCwiZXhwIjoxNzM1NzQ1MTI0fQ.K_6K7xWxnCLLBMW3g1SYanGqZAxUmwCJ0m1PhUter7k"
            },
            "coords": [
                [
                    12.9883,
                    55.58852
                ],
                [
                    12.98846,
                    55.58849
                ],
                [
                    12.98869,
                    55.58846
                ],
                [
                    12.98877,
                    55.58845
                ],
                [
                    12.98909,
                    55.58833
                ],
                [
                    12.98897,
                    55.58824
                ],
                [
                    12.9889,
                    55.58815
                ],
                [
                    12.98882,
                    55.58803
                ],
                [
                    12.98874,
                    55.58804
                ],
                [
                    12.98843,
                    55.58811
                ],
                [
                    12.98833,
                    55.58811
                ],
                [
                    12.98734,
                    55.58831
                ],
                [
                    12.98705,
                    55.58836
                ],
                [
                    12.98659,
                    55.58845
                ],
                [
                    12.98611,
                    55.58859
                ],
                [
                    12.98594,
                    55.58864
                ],
                [
                    12.98602,
                    55.58879
                ],
                [
                    12.986,
                    55.58887
                ],
                [
                    12.98596,
                    55.58891
                ],
                [
                    12.98593,
                    55.58894
                ],
                [
                    12.9856,
                    55.58924
                ],
                [
                    12.98531,
                    55.58971
                ],
                [
                    12.98525,
                    55.58993
                ],
                [
                    12.98454,
                    55.58992
                ]
            ]
        }
    ]
}